RaichuNorm-1.1.data/scripts/raichu
raichu/__init__.py
raichu/util.py
RaichuNorm-1.1.dist-info/LICENSE
RaichuNorm-1.1.dist-info/METADATA
RaichuNorm-1.1.dist-info/WHEEL
RaichuNorm-1.1.dist-info/top_level.txt
RaichuNorm-1.1.dist-info/RECORD
