Metadata-Version: 2.1
Name: RaichuNorm
Version: 1.1
Summary: A cross-platform method for chromatin contact normalization
Home-page: https://github.com/XiaoTaoWang/Raichu
Author: XiaoTao Wang
Author-email: wangxiaotao@fudan.edu.cn
Keywords: Hi-C ChIA-PET HiChIP PLAC-Seq single-cell normalization
Classifier: Programming Language :: Python :: 3 :: Only
Classifier: Operating System :: POSIX
Classifier: Development Status :: 3 - Alpha
Classifier: Intended Audience :: Science/Research
Classifier: Topic :: Scientific/Engineering :: Bio-Informatics
License-File: LICENSE
